{
  "vans": [
    {
      "id": 1,
      "isUrgent": false,
      "isLoaded": true
    },
    {
      "id": 2,
      "isUrgent": true,
      "isLoaded": false
    },
    {
      "id": 3,
      "isUrgent": false,
      "isLoaded": true
    },
    {
      "id": 4,
      "isUrgent": true,
      "isLoaded": false
    },
    {
      "id": 5,
      "isUrgent": false,
      "isLoaded": true
    },
    {
      "id": 6,
      "isUrgent": true,
      "isLoaded": false
    },
    {
      "id": 7,
      "isUrgent": false,
      "isLoaded": true
    },
    {
      "id": 8,
      "isUrgent": true,
      "isLoaded": false
    },
    {
      "id": 9,
      "isUrgent": false,
      "isLoaded": true
    },
    {
      "id": 10,
      "isUrgent": true,
      "isLoaded": false
    }
  ]
}